simulib/__init__.py
simulib/entities/__init__.py
simulib/entities/dynamic.py
simulib/entities/steadystate.py
simulib/io/__init__.py
simulib/io/utils.py
simulib/io/dynamic/__init__.py
simulib/io/dynamic/importers.py
simulib/methods/__init__.py
simulib/methods/dynamic/exceptions.py
simulib/methods/dynamic/dfba/__init__.py
simulib/methods/dynamic/dfba/entities.py
simulib/methods/dynamic/dfba/simulator.py
simulib/utils/__init__.py
simulib/utils/expression.py
simulib-0.1.0.dist-info/licenses/LICENSE
simulib-0.1.0.dist-info/METADATA
simulib-0.1.0.dist-info/WHEEL
simulib-0.1.0.dist-info/top_level.txt
simulib-0.1.0.dist-info/RECORD
