Metadata-Version: 2.4
Name: simulib
Version: 0.1.0
Summary: A library that wraps metabolic simulation methods from various frameworks and provides a common framework for input and output handling
Author-email: Vitor Vieira <vvieira@amyris.com>, Joao Fonseca <jfonseca@amyris.com>
License:                                  Apache License
Classifier: Development Status :: 5 - Production/Stable
Classifier: Intended Audience :: Science/Research
Classifier: License :: OSI Approved :: Apache Software License
Classifier: Programming Language :: Python :: 3.10
Classifier: Topic :: Scientific/Engineering :: Bio-Informatics
Classifier: Natural Language :: English
Requires-Python: <3.11,>=3.8
License-File: LICENSE
Requires-Dist: typing_extensions
Requires-Dist: matplotlib
Requires-Dist: sympy
Requires-Dist: cobra
Requires-Dist: numpy
Requires-Dist: pydantic
Requires-Dist: pandas
Requires-Dist: PyYAML
Provides-Extra: dfba
Requires-Dist: dfba==0.1.8; extra == "dfba"
Dynamic: license-file
